montecarlo_nystrom/__init__.py
montecarlo_nystrom/__main__.py
montecarlo_nystrom/_main.py
montecarlo_nystrom/cli.py
montecarlo_nystrom/py.typed
montecarlo_nystrom-1.1.0.dist-info/licenses/LICENSE
montecarlo_nystrom-1.1.0.dist-info/METADATA
montecarlo_nystrom-1.1.0.dist-info/WHEEL
montecarlo_nystrom-1.1.0.dist-info/entry_points.txt
montecarlo_nystrom-1.1.0.dist-info/top_level.txt
montecarlo_nystrom-1.1.0.dist-info/RECORD
