Metadata-Version: 2.4
Name: montecarlo-nystrom
Version: 1.1.0
Summary: Monte-Carlo Nystrom method in NumPy / PyTorch
Author-email: ultrasphere-dev <34j.95a2p@simplelogin.com>
License-Expression: MIT
Project-URL: Bug Tracker, https://github.com/ultrasphere-dev/montecarlo-nystrom/issues
Project-URL: Changelog, https://github.com/ultrasphere-dev/montecarlo-nystrom/blob/main/CHANGELOG.md
Project-URL: documentation, https://montecarlo-nystrom.readthedocs.io
Project-URL: repository, https://github.com/ultrasphere-dev/montecarlo-nystrom
Classifier: Development Status :: 2 - Pre-Alpha
Classifier: Intended Audience :: Developers
Classifier: Natural Language :: English
Classifier: Operating System :: OS Independent
Classifier: Programming Language :: Python :: 3.10
Classifier: Programming Language :: Python :: 3.11
Classifier: Programming Language :: Python :: 3.12
Classifier: Programming Language :: Python :: 3.13
Classifier: Programming Language :: Python :: 3.14
Classifier: Topic :: Software Development :: Libraries
Requires-Python: >=3.12
License-File: LICENSE
Requires-Dist: array-api-compat>=1.12.0
Requires-Dist: array-api-extra>=0.9.0
Requires-Dist: cyclopts>=3.24.0
Requires-Dist: matplotlib>=3.10.7
Requires-Dist: numpy>=2.2.6
Requires-Dist: types-array-api>=1.1.4
Requires-Dist: ultrasphere>=2.0.4
Dynamic: license-file
